anti_recaptcha/__init__.py
anti_recaptcha/exceptions.py
anti_recaptcha/session.py
anti_recaptcha/sites.py
anti_recaptcha/structs.py
anti_recaptcha/utils.py
anti_recaptcha/reCaptchaV2/__init__.py
anti_recaptcha/reCaptchaV3/__init__.py
anti_recaptcha/reCaptchaV3/constants.py
anti_recaptcha-0.0.5.dist-info/licenses/LICENSE
anti_recaptcha-0.0.5.dist-info/METADATA
anti_recaptcha-0.0.5.dist-info/WHEEL
anti_recaptcha-0.0.5.dist-info/top_level.txt
anti_recaptcha-0.0.5.dist-info/RECORD
