Metadata-Version: 2.4
Name: anti-recaptcha
Version: 0.0.5
Summary: Automated reCAPTCHA V2 and V3 solver using Selenium for Python bots.
Home-page: https://github.com/dragon0041/anti-recaptcha
Author: Dragon
Author-email: aherodragon41@gmail.com
License: MIT
Keywords: recaptcha solver,recaptcha,bypass recaptcha,anti recaptcha,google recaptcha,captcha solver,captcha bypass,solve captcha,auto captcha solve,recaptcha v2,recaptcha v3,v2 captcha solver,v3 captcha solver,google captcha,captcha breaker,recaptcha breaker,python recaptcha solver,recaptcha solver python,ai captcha solver,machine learning captcha solver,deep learning captcha,captcha automation,captcha bot,recaptcha bot,selenium recaptcha,selenium captcha solver,selenium recaptcha solver,undete
Platform: all
Classifier: Development Status :: 5 - Production/Stable
Classifier: Intended Audience :: Developers
Classifier: License :: OSI Approved :: MIT License
Classifier: Topic :: Software Development :: Libraries :: Python Modules
Classifier: Programming Language :: Python
Requires-Python: >=3.7,<3.13
License-File: LICENSE
Requires-Dist: requests<3.0,>=2.25.1
Requires-Dist: PySocks==1.7.1
Requires-Dist: SpeechRecognition==3.8.1
Requires-Dist: pydub==0.25.1
Requires-Dist: selenium
Dynamic: author
Dynamic: author-email
Dynamic: classifier
Dynamic: description
Dynamic: description-content-type
Dynamic: home-page
Dynamic: keywords
Dynamic: license
Dynamic: license-file
Dynamic: platform
Dynamic: requires-dist
Dynamic: requires-python
Dynamic: summary
